trytond/modules/health_disability/COPYING
trytond/modules/health_disability/README.rst
trytond/modules/health_disability/__init__.py
trytond/modules/health_disability/data/activity_and_participation.xml
trytond/modules/health_disability/data/body_functions.xml
trytond/modules/health_disability/data/body_structures.xml
trytond/modules/health_disability/data/categories.xml
trytond/modules/health_disability/data/environmental_factors.xml
trytond/modules/health_disability/health_disability.py
trytond/modules/health_disability/health_disability_view.xml
trytond/modules/health_disability/locale/ar.po
trytond/modules/health_disability/locale/de.po
trytond/modules/health_disability/locale/el.po
trytond/modules/health_disability/locale/eo.po
trytond/modules/health_disability/locale/es.po
trytond/modules/health_disability/locale/fr.po
trytond/modules/health_disability/locale/health_disability.pot
trytond/modules/health_disability/locale/it_IT.po
trytond/modules/health_disability/locale/ja_JP.po
trytond/modules/health_disability/locale/ka.po
trytond/modules/health_disability/locale/lo.po
trytond/modules/health_disability/locale/pt_BR.po
trytond/modules/health_disability/locale/sv.po
trytond/modules/health_disability/locale/tr.po
trytond/modules/health_disability/locale/uk.po
trytond/modules/health_disability/locale/zh_CN.po
trytond/modules/health_disability/pyproject.toml
trytond/modules/health_disability/tests/__init__.py
trytond/modules/health_disability/tests/test_health_disability.py
trytond/modules/health_disability/tryton.cfg
trytond/modules/health_disability/view/gnuhealth_activity_and_participation_assessment_form.xml
trytond/modules/health_disability/view/gnuhealth_activity_and_participation_assessment_tree.xml
trytond/modules/health_disability/view/gnuhealth_activity_and_participation_form.xml
trytond/modules/health_disability/view/gnuhealth_activity_and_participation_tree.xml
trytond/modules/health_disability/view/gnuhealth_body_function_assessment_form.xml
gnuhealth_disability-5.0.2.dist-info/METADATA
gnuhealth_disability-5.0.2.dist-info/WHEEL
gnuhealth_disability-5.0.2.dist-info/licenses/COPYING
gnuhealth_disability-5.0.2.dist-info/RECORD
